examples/bert/BertBase.py
examples/bert/BertForVi.py
examples/simpleDemo/client.py
examples/simpleDemo/server.py
examples/stream_demo/client.py
examples/stream_demo/server.py
tzrpc/__init__.py
tzrpc/client/client.py
tzrpc/decorator/rpc.py
tzrpc/decorator/singleton.py
tzrpc/exceptions/exceptions.py
tzrpc/proto/py/Boolean_pb2.py
tzrpc/proto/py/Boolean_pb2_grpc.py
tzrpc/proto/py/Bytes_pb2.py
tzrpc/proto/py/Bytes_pb2_grpc.py
tzrpc/proto/py/Number_pb2.py
tzrpc/proto/py/Number_pb2_grpc.py
tzrpc/proto/py/Numpy_pb2.py
tzrpc/proto/py/Numpy_pb2_grpc.py
tzrpc/proto/py/Server_pb2.py
tzrpc/proto/py/Server_pb2_grpc.py
tzrpc/proto/py/String_pb2.py
tzrpc/proto/py/String_pb2_grpc.py
tzrpc/proto/py/Tensor_pb2.py
tzrpc/proto/py/Tensor_pb2_grpc.py
tzrpc/server/__init__.py
tzrpc/server/base.py
tzrpc/server/server.py
tzrpc/utils/constant.py
tzrpc/utils/logger.py
tzrpc/utils/numpy_serialized.py
tzrpc-0.0.4.dist-info/LICENSE
tzrpc-0.0.4.dist-info/METADATA
tzrpc-0.0.4.dist-info/WHEEL
tzrpc-0.0.4.dist-info/top_level.txt
tzrpc-0.0.4.dist-info/RECORD
