Metadata-Version: 2.1
Name: tzrpc
Version: 0.0.4
Summary: a rpc framework for python base on grpc
Home-page: https://github.com/lovemefan/TZRPC
Author: Lovemefan, Yunnan Key Laboratory of Artificial Intelligence, Kunming University of Science and Technology, Kunming, Yunnan 
Author-email: lovemefan@outlook.com
License: UNKNOWN
Platform: UNKNOWN
Classifier: Programming Language :: Python :: 3.7
Classifier: Programming Language :: Python :: 3.8
Classifier: Programming Language :: Python :: 3.9
Classifier: License :: OSI Approved :: MIT License
Classifier: Operating System :: OS Independent
Requires-Python: >=3.7.0
Requires-Dist: grpcio ==1.40.0
Requires-Dist: grpcio-tools ==1.40.0
Requires-Dist: numpy
